odoo/addons/partner_code_program_purchase/README.rst
odoo/addons/partner_code_program_purchase/__init__.py
odoo/addons/partner_code_program_purchase/__manifest__.py
odoo/addons/partner_code_program_purchase/i18n/es.po
odoo/addons/partner_code_program_purchase/models/__init__.py
odoo/addons/partner_code_program_purchase/models/purchase_order.py
odoo/addons/partner_code_program_purchase/models/purchase_report.py
odoo/addons/partner_code_program_purchase/readme/CONFIGURE.md
odoo/addons/partner_code_program_purchase/readme/CONTRIBUTORS.md
odoo/addons/partner_code_program_purchase/readme/DESCRIPTION.md
odoo/addons/partner_code_program_purchase/readme/INSTALL.md
odoo/addons/partner_code_program_purchase/readme/USAGE.md
odoo/addons/partner_code_program_purchase/static/description/icon.png
odoo/addons/partner_code_program_purchase/static/description/index.html
odoo/addons/partner_code_program_purchase/tests/__init__.py
odoo/addons/partner_code_program_purchase/tests/test_partner_code_program_purchase.py
odoo/addons/partner_code_program_purchase/views/purchase_order.xml
odoo/addons/partner_code_program_purchase/views/purchase_report.xml
odoo_addon_partner_code_program_purchase-18.0.1.0.0.1.dist-info/METADATA
odoo_addon_partner_code_program_purchase-18.0.1.0.0.1.dist-info/WHEEL
odoo_addon_partner_code_program_purchase-18.0.1.0.0.1.dist-info/top_level.txt
odoo_addon_partner_code_program_purchase-18.0.1.0.0.1.dist-info/RECORD
